rqdatac_hk/__init__.py
rqdatac_hk/_version.py
rqdatac_hk/api.py
rqdatac_hk-0.3.dist-info/METADATA
rqdatac_hk-0.3.dist-info/WHEEL
rqdatac_hk-0.3.dist-info/top_level.txt
rqdatac_hk-0.3.dist-info/RECORD
