Metadata-Version: 2.4
Name: rqdatac_hk
Version: 0.3
Summary: Project Short Description
Author-email: Ricequant <public@ricequant.com>
Project-URL: Homepage, https://www.ricequant.com/
Keywords: rqdatac_hk
Classifier: Programming Language :: Python :: 3
Classifier: Programming Language :: Python :: 3.7
Classifier: Programming Language :: Python :: 3.8
Classifier: Programming Language :: Python :: 3.9
Classifier: Programming Language :: Python :: 3.10
Classifier: Programming Language :: Python :: 3.11
Classifier: Intended Audience :: Developers
Classifier: Operating System :: OS Independent
Classifier: Environment :: Console
Requires-Python: >=3.7
Requires-Dist: rqdatac>=3.2.1
